receipts/__init__.py
receipts/admin.py
receipts/apps.py
receipts/models.py
receipts/tests.py
receipts/urls.py
receipts/views.py
receipts/migrations/0001_initial.py
receipts/migrations/__init__.py
realpython_django_receipts-1.1.0.dist-info/LICENSE
realpython_django_receipts-1.1.0.dist-info/METADATA
realpython_django_receipts-1.1.0.dist-info/WHEEL
realpython_django_receipts-1.1.0.dist-info/top_level.txt
realpython_django_receipts-1.1.0.dist-info/RECORD
